{
  "total_lines": 10742,
  "covered_lines": 10277,
  "coverage_percent": 95.67,
  "breakdown": {
    "backend": {
      "total_lines": 6919,
      "covered_lines": 6718,
      "coverage_percent": 97.09,
      "file_count": 89
    },
    "frontend": {
      "total_lines": 1669,
      "covered_lines": 1496,
      "coverage_percent": 89.63,
      "file_count": 50
    },
    "scripts": {
      "total_lines": 2154,
      "covered_lines": 2063,
      "coverage_percent": 95.78,
      "file_count": 38
    }
  }
}
